LICENSE
LICENSE.txt
README.rst
setup.cfg
setup.py
KNlibrary/__init__.py
KNlibrary/kninfo.py
KNlibrary.egg-info/PKG-INFO
KNlibrary.egg-info/SOURCES.txt
KNlibrary.egg-info/dependency_links.txt
KNlibrary.egg-info/top_level.txt